{"_type":"export","__export_format":4,"__export_date":"2019-12-10T22:56:59.191Z","__export_source":"insomnia.desktop.app:v7.0.5","resources":[{"_id":"req_12f9b0a52e024ef3a9f4e47cef10ffe8","authentication":{"token":"eyJhbGciOiJIUzI1NiIsInR5cCI6IkpXVCJ9.eyJpZCI6NSwiaWF0IjoxNTc2MDE4MTIwLCJleHAiOjE1NzY2MjI5MjB9.RgpLfz9RtKVsjAojDxvG3UOrbBzEHr8rRCCpmlnUWq4","type":"bearer"},"body":{},"created":1576017605234,"description":"","headers":[],"isPrivate":false,"metaSortKey":-1576017605234,"method":"GET","modified":1576018130307,"name":"List","parameters":[],"parentId":"fld_6baa2ce3a70f434491536901e61fc93c","settingDisableRenderRequestBody":false,"settingEncodeUrl":true,"settingFollowRedirects":"global","settingRebuildPath":true,"settingSendCookies":true,"settingStoreCookies":true,"url":"{{ base_url  }}/notifications","_type":"request"},{"_id":"fld_6baa2ce3a70f434491536901e61fc93c","created":1576017595524,"description":"","environment":{},"environmentPropertyOrder":null,"metaSortKey":-1576017595524,"modified":1576017595524,"name":"Notifications","parentId":"wrk_f6c4f41fe2754f18b9b363ba45092536","_type":"request_group"},{"_id":"wrk_f6c4f41fe2754f18b9b363ba45092536","created":1574690731812,"description":"","modified":1574690731812,"name":"GoBarber","parentId":null,"_type":"workspace"},{"_id":"req_99ea65b8637a491888c39490420675c4","authentication":{"token":"eyJhbGciOiJIUzI1NiIsInR5cCI6IkpXVCJ9.eyJpZCI6NSwiaWF0IjoxNTc2MDA3NDIwLCJleHAiOjE1NzY2MTIyMjB9._nMQpDgE9mlXHdg-6fDEX7g-HZzHFRIvHcsh--9liQQ","type":"bearer"},"body":{},"created":1576009542078,"description":"","headers":[],"isPrivate":false,"metaSortKey":-1576009542078,"method":"GET","modified":1576010023851,"name":"List","parameters":[{"description":"","id":"pair_1438d4423d2e432aa0c1b0f9fb0109d7","name":"date","value":"2019-12-11T00:00-03:00"}],"parentId":"fld_08311298b50d4c0681e1508a0538dd1e","settingDisableRenderRequestBody":false,"settingEncodeUrl":true,"settingFollowRedirects":"global","settingRebuildPath":true,"settingSendCookies":true,"settingStoreCookies":true,"url":"{{ base_url  }}/schedule","_type":"request"},{"_id":"fld_08311298b50d4c0681e1508a0538dd1e","created":1576009534193,"description":"","environment":{},"environmentPropertyOrder":null,"metaSortKey":-1576009534193,"modified":1576009534193,"name":"Schedule","parentId":"wrk_f6c4f41fe2754f18b9b363ba45092536","_type":"request_group"},{"_id":"req_50d87d32efc94af38b5ad8440a7ccf58","authentication":{"token":"{{ token  }}","type":"bearer"},"body":{},"created":1576006159720,"description":"","headers":[],"isPrivate":false,"metaSortKey":-1576003608793,"method":"GET","modified":1576009932919,"name":"List","parameters":[{"description":"","id":"pair_97694c6d34ef4b6da05882adf67393a7","name":"page","value":"1"}],"parentId":"fld_f77c453bdf394c73895c474b1c653e8f","settingDisableRenderRequestBody":false,"settingEncodeUrl":true,"settingFollowRedirects":"global","settingRebuildPath":true,"settingSendCookies":true,"settingStoreCookies":true,"url":"{{ base_url  }}/appointments","_type":"request"},{"_id":"fld_f77c453bdf394c73895c474b1c653e8f","created":1576003592840,"description":"","environment":{},"environmentPropertyOrder":null,"metaSortKey":-1576003592840,"modified":1576003592840,"name":"Appointments","parentId":"wrk_f6c4f41fe2754f18b9b363ba45092536","_type":"request_group"},{"_id":"req_96ca91a11fb14535bc272df6e7ea4457","authentication":{"token":"{{ token  }}","type":"bearer"},"body":{"mimeType":"application/json","text":"{\n\t\"provider_id\": 5,\n\t\"date\": \"2019-12-20T10:00:00-03:00\"\n}"},"created":1576003608742,"description":"","headers":[{"id":"pair_14079d2954fb49d5baef32739fa76549","name":"Content-Type","value":"application/json"}],"isPrivate":false,"metaSortKey":-1576003608743,"method":"POST","modified":1576018226807,"name":"Create","parameters":[],"parentId":"fld_f77c453bdf394c73895c474b1c653e8f","settingDisableRenderRequestBody":false,"settingEncodeUrl":true,"settingFollowRedirects":"global","settingRebuildPath":true,"settingSendCookies":true,"settingStoreCookies":true,"url":"{{ base_url  }}/appointments","_type":"request"},{"_id":"req_6f98a9fc2a1b4196a1c7ed7fbf1ca408","authentication":{"token":"{{ token  }}","type":"bearer"},"body":{"mimeType":"application/json","text":""},"created":1575911769907,"description":"","headers":[{"name":"Content-Type","value":"application/json"}],"isPrivate":false,"metaSortKey":-1575911769907,"method":"GET","modified":1575911797945,"name":"Index","parameters":[],"parentId":"fld_c471a02849b1448da8db52aa14080c64","settingDisableRenderRequestBody":false,"settingEncodeUrl":true,"settingFollowRedirects":"global","settingRebuildPath":true,"settingSendCookies":true,"settingStoreCookies":true,"url":"{{ base_url  }}/providers","_type":"request"},{"_id":"fld_c471a02849b1448da8db52aa14080c64","created":1575911762830,"description":"","environment":{},"environmentPropertyOrder":null,"metaSortKey":-1575911762830,"modified":1575911762830,"name":"Providers","parentId":"wrk_f6c4f41fe2754f18b9b363ba45092536","_type":"request_group"},{"_id":"req_49db61cec0b04cdd9497afc801170559","authentication":{},"body":{"mimeType":"multipart/form-data","params":[{"description":"","fileName":"/home/juca/Pictures/Profile/GTO.jpg","id":"pair_659eb435cb3b42c98f3e77043911756b","name":"file","type":"file","value":"{% file '' %}"}]},"created":1575902887826,"description":"","headers":[{"id":"pair_2af85b09e8d8436f8126bcea406bfa51","name":"Content-Type","value":"multipart/form-data"}],"isPrivate":false,"metaSortKey":-1575902887827,"method":"POST","modified":1575903103911,"name":"Create","parameters":[],"parentId":"wrk_f6c4f41fe2754f18b9b363ba45092536","settingDisableRenderRequestBody":false,"settingEncodeUrl":true,"settingFollowRedirects":"global","settingRebuildPath":true,"settingSendCookies":true,"settingStoreCookies":true,"url":"{{ base_url  }}/files","_type":"request"},{"_id":"req_f083e39f4f48436d8c66b3301ec7c07b","authentication":{"token":"{{ token  }}","type":"bearer"},"body":{"mimeType":"multipart/form-data","params":[{"description":"","fileName":"/home/juca/Pictures/Profile/GTO.jpg","id":"pair_335a25eead254b0aa5bc72facdda2560","name":"file","type":"file","value":""}]},"created":1575903155065,"description":"","headers":[{"id":"pair_c5489c2a34174f8bad5159434ea7fc4e","name":"Content-Type","value":"multipart/form-data"}],"isPrivate":false,"metaSortKey":-1575903155065,"method":"POST","modified":1575904249523,"name":"Create","parameters":[],"parentId":"fld_c3761ecddbed4c4089e92499e2ca8dca","settingDisableRenderRequestBody":false,"settingEncodeUrl":true,"settingFollowRedirects":"global","settingRebuildPath":true,"settingSendCookies":true,"settingStoreCookies":true,"url":"{{ base_url  }}/files","_type":"request"},{"_id":"fld_c3761ecddbed4c4089e92499e2ca8dca","created":1575902854082,"description":"","environment":{},"environmentPropertyOrder":null,"metaSortKey":-1575902854082,"modified":1575902854082,"name":"Files","parentId":"wrk_f6c4f41fe2754f18b9b363ba45092536","_type":"request_group"},{"_id":"req_45d7018aec794a38bfe812d53144526c","authentication":{},"body":{"mimeType":"application/json","text":"{\n  \"email\": \"teste3@teste.com\",\n  \"password\": \"123\"\n}"},"created":1574792045698,"description":"","headers":[{"id":"pair_22ced84135b940a0b6b268244289d540","name":"Content-Type","value":"application/json"}],"isPrivate":false,"metaSortKey":-1574792045698,"method":"POST","modified":1575903218414,"name":"Create","parameters":[],"parentId":"fld_4d0320398ef542ec80923870674e5f6b","settingDisableRenderRequestBody":false,"settingEncodeUrl":true,"settingFollowRedirects":"global","settingRebuildPath":true,"settingSendCookies":true,"settingStoreCookies":true,"url":"{{ base_url  }}/sessions","_type":"request"},{"_id":"fld_4d0320398ef542ec80923870674e5f6b","created":1574792023589,"description":"","environment":{},"environmentPropertyOrder":null,"metaSortKey":-1574792023589,"modified":1574792023589,"name":"Sessions","parentId":"wrk_f6c4f41fe2754f18b9b363ba45092536","_type":"request_group"},{"_id":"req_e07eaa8082df4636b9c912b7f70b9c26","authentication":{},"body":{"mimeType":"application/json","text":"{\n  \"email\": \"juca1@test.com\",\n\t\"password\": \"123456\"\n}"},"created":1575910697106,"description":"","headers":[{"id":"pair_22ced84135b940a0b6b268244289d540","name":"Content-Type","value":"application/json"}],"isPrivate":false,"metaSortKey":-1574741455953.5,"method":"POST","modified":1575911054118,"name":"Create (Copy)","parameters":[],"parentId":"fld_4d0320398ef542ec80923870674e5f6b","settingDisableRenderRequestBody":false,"settingEncodeUrl":true,"settingFollowRedirects":"global","settingRebuildPath":true,"settingSendCookies":true,"settingStoreCookies":true,"url":"{{ base_url  }}/sessions","_type":"request"},{"_id":"req_04973b7cb43a47949fbe36880aa82fb7","authentication":{},"body":{"mimeType":"application/json","text":"{\n  \"email\": \"juca1@test.com\",\n\t\"password\": \"1234\"\n}"},"created":1576007407218,"description":"","headers":[{"id":"pair_22ced84135b940a0b6b268244289d540","name":"Content-Type","value":"application/json"}],"isPrivate":false,"metaSortKey":-1574716161081.25,"method":"POST","modified":1576018119322,"name":"Create (Copy) (Copy)","parameters":[],"parentId":"fld_4d0320398ef542ec80923870674e5f6b","settingDisableRenderRequestBody":false,"settingEncodeUrl":true,"settingFollowRedirects":"global","settingRebuildPath":true,"settingSendCookies":true,"settingStoreCookies":true,"url":"{{ base_url  }}/sessions","_type":"request"},{"_id":"req_afee057824684361880d47bdacbb8d77","authentication":{"disabled":false,"token":"{{ token  }}","type":"bearer"},"body":{"mimeType":"application/json","text":"{\n\t\"name\": \"Juca\",\n  \"email\": \"teste3@teste.com\",\n\t\"oldPassword\": \"123\",\n\t\"password\": \"1234\",\n\t\"confirmPassword\": \"1234\",\n\t\"avatar_id\": 1\n}"},"created":1574795165486,"description":"","headers":[{"id":"pair_56aee336d80a4477b699863f1086e231","name":"Content-Type","value":"application/json"}],"isPrivate":false,"metaSortKey":-1574795165486,"method":"PUT","modified":1575906521512,"name":"Update","parameters":[],"parentId":"fld_3d24003ec7ed46d7b9215c182cbd3fbd","settingDisableRenderRequestBody":false,"settingEncodeUrl":true,"settingFollowRedirects":"global","settingRebuildPath":true,"settingSendCookies":true,"settingStoreCookies":true,"url":"{{ base_url  }}/users","_type":"request"},{"_id":"fld_3d24003ec7ed46d7b9215c182cbd3fbd","created":1574690750835,"description":"","environment":{},"environmentPropertyOrder":null,"metaSortKey":-1574690750836,"modified":1574690750835,"name":"Users","parentId":"wrk_f6c4f41fe2754f18b9b363ba45092536","_type":"request_group"},{"_id":"req_cc7e410cf69e4bbc8dd7021527c21669","authentication":{"disabled":false,"token":"eyJhbGciOiJIUzI1NiIsInR5cCI6IkpXVCJ9.eyJpZCI6NCwiaWF0IjoxNTc1OTEwNzAzLCJleHAiOjE1NzY1MTU1MDN9.CnQLUp8Zj9gQ1HQ0-0nlM8oZfP_1dg1ink_qfRJUy60","type":"bearer"},"body":{"mimeType":"application/json","text":"{\n\t\"name\": \"Reinaldo\",\n  \"email\": \"juca1@teste.com\",\n\t\"oldPassword\": \"123\",\n\t\"password\": \"12345678\",\n\t\"confirmPassword\": \"12345678\",\n\t\"avatar_id\": 1\n}"},"created":1575500744731,"description":"","headers":[{"id":"pair_56aee336d80a4477b699863f1086e231","name":"Content-Type","value":"application/json"}],"isPrivate":false,"metaSortKey":-1574793605592,"method":"PUT","modified":1575911295838,"name":"Update (1)","parameters":[],"parentId":"fld_3d24003ec7ed46d7b9215c182cbd3fbd","settingDisableRenderRequestBody":false,"settingEncodeUrl":true,"settingFollowRedirects":"global","settingRebuildPath":true,"settingSendCookies":true,"settingStoreCookies":true,"url":"{{ base_url  }}/users","_type":"request"},{"_id":"req_19205f7689ce46ae9d06a9da67b420f8","authentication":{"disabled":false,"token":"eyJhbGciOiJIUzI1NiIsInR5cCI6IkpXVCJ9.eyJpZCI6NSwiaWF0IjoxNTc2MDA3NDIwLCJleHAiOjE1NzY2MTIyMjB9._nMQpDgE9mlXHdg-6fDEX7g-HZzHFRIvHcsh--9liQQ","type":"bearer"},"body":{"mimeType":"application/json","text":"{\n\t\"name\": \"Adão\",\n  \"email\": \"juca1@test.com\",\n\t\"oldPassword\": \"123\",\n\t\"password\": \"1234\",\n\t\"confirmPassword\": \"1234\",\n\t\"avatar_id\": 1\n}"},"created":1576007467367,"description":"","headers":[{"id":"pair_56aee336d80a4477b699863f1086e231","name":"Content-Type","value":"application/json"}],"isPrivate":false,"metaSortKey":-1574792825645,"method":"PUT","modified":1576007616045,"name":"Update (1) (Copy)","parameters":[],"parentId":"fld_3d24003ec7ed46d7b9215c182cbd3fbd","settingDisableRenderRequestBody":false,"settingEncodeUrl":true,"settingFollowRedirects":"global","settingRebuildPath":true,"settingSendCookies":true,"settingStoreCookies":true,"url":"{{ base_url  }}/users","_type":"request"},{"_id":"req_be821ea6bc9f4ceeb32a59bcfb2664ab","authentication":{},"body":{"mimeType":"application/json","text":"{\n\t\"name\": \"Juca\",\n  \"email\": \"juca1@test.com\",\n  \"password\": \"123456\"\n}"},"created":1574690866209,"description":"","headers":[{"id":"pair_a73a068a090d4d18a4692d524db41ffd","name":"Content-Type","value":"application/json"}],"isPrivate":false,"metaSortKey":-1574690866209,"method":"POST","modified":1575910681335,"name":"Create","parameters":[],"parentId":"fld_3d24003ec7ed46d7b9215c182cbd3fbd","settingDisableRenderRequestBody":false,"settingEncodeUrl":true,"settingFollowRedirects":"global","settingRebuildPath":true,"settingSendCookies":true,"settingStoreCookies":true,"url":"{{ base_url  }}/users","_type":"request"},{"_id":"env_6569dd52a9f4a7c1df58ab85f22c1dfdbab4bf71","color":null,"created":1574690731892,"data":{"base_url":"http://localhost:3333","token":"eyJhbGciOiJIUzI1NiIsInR5cCI6IkpXVCJ9.eyJpZCI6MSwiaWF0IjoxNTc1OTAzMjMzLCJleHAiOjE1NzY1MDgwMzN9.w4EEpimujn8XjeG-qw2SpbjWDlM3iqQsAk5f3LP8DXk"},"dataPropertyOrder":{"&":["base_url","token"]},"isPrivate":false,"metaSortKey":1574690731892,"modified":1575903272376,"name":"Base Environment","parentId":"wrk_f6c4f41fe2754f18b9b363ba45092536","_type":"environment"},{"_id":"jar_6569dd52a9f4a7c1df58ab85f22c1dfdbab4bf71","cookies":[],"created":1574690731894,"modified":1574690731894,"name":"Default Jar","parentId":"wrk_f6c4f41fe2754f18b9b363ba45092536","_type":"cookie_jar"}]}